assemblyline_incident_manager/__init__.py
assemblyline_incident_manager/al_incident_analyzer.py
assemblyline_incident_manager/al_incident_downloader.py
assemblyline_incident_manager/al_incident_submitter.py
assemblyline_incident_manager/helper.py
assemblyline_incident_manager-4.0.5.dist-info/METADATA
assemblyline_incident_manager-4.0.5.dist-info/WHEEL
assemblyline_incident_manager-4.0.5.dist-info/entry_points.txt
assemblyline_incident_manager-4.0.5.dist-info/top_level.txt
assemblyline_incident_manager-4.0.5.dist-info/RECORD
