Metadata-Version: 2.1
Name: assemblyline-incident-manager
Version: 4.0.5
Summary: Assemblyline v4 client incident manager library
Home-page: https://github.com/CybercentreCanada/assemblyline-incident-manager
Author: CSE-CST Assemblyline development team
Author-email: assemblyline@cyber.gc.ca
License: MIT
Keywords: development assemblyline client incident gc canada cse-cst cse cst
Platform: UNKNOWN
Classifier: Development Status :: 5 - Production/Stable
Classifier: Intended Audience :: Developers
Classifier: Topic :: Software Development :: Libraries
Classifier: License :: OSI Approved :: MIT License
Classifier: Programming Language :: Python :: 3.6
Classifier: Programming Language :: Python :: 3.7
Classifier: Programming Language :: Python :: 3.8
Requires-Dist: assemblyline-client
Requires-Dist: click
Provides-Extra: test
Requires-Dist: pytest ; extra == 'test'
Requires-Dist: pytest-mock ; extra == 'test'
